[{"count":6},{"id":"PR-1","name":"laptop","price":1000,"description":"This is is a T-shirt"},{"id":"PR-2","name":"hi","price":23,"description":"A cup"},{"id":"PR-3","name":"again","price":3,"description":"Your best kind of laptop"},{"id":"PR-4","name":"phone","price":345,"description":"Best of it kind"},{"id":"PR-5","name":"cylinder","price":33,"description":"A cooking cylinder"},{"id":"PR-6","name":"laptop","price":222,"description":"awzaESRXDTCFGVHJBNNNNNNNNNNNNNNNNNNNNNNNNNNNNNNNNNNNNNNNNNNN"}]